{
  "skills": [
    {"skill_id": "gather_pine_branches", "x": 0, "y": 0},
    {"skill_id": "assemble_tree_base", "x": -2, "y": 2},
    {"skill_id": "plant_the_tree", "x": 0, "y": 2},
    {"skill_id": "strengthen_roots", "x": 2, "y": 2},
    {"skill_id": "support_trunk", "x": 0, "y": 4},
    {"skill_id": "string_first_light", "x": -4, "y": 6},
    {"skill_id": "add_red_lights", "x": -2, "y": 6},
    {"skill_id": "add_green_lights", "x": 0, "y": 6},
    {"skill_id": "add_blue_lights", "x": 2, "y": 6},
    {"skill_id": "pattern_first_ring", "x": -1, "y": 8},
    {"skill_id": "light_spiral", "x": 1, "y": 8},
    {"skill_id": "synchronize_lights", "x": 0, "y": 10},
    {"skill_id": "hang_gold_ornaments", "x": -3, "y": 12},
    {"skill_id": "hang_silver_ornaments", "x": -1, "y": 12},
    {"skill_id": "hang_red_ornaments", "x": 1, "y": 12},
    {"skill_id": "ornament_patterns", "x": 0, "y": 14},
    {"skill_id": "balance_ornament_weight", "x": 2, "y": 12},
    {"skill_id": "sparkly_ornaments", "x": 3, "y": 14},
    {"skill_id": "string_green_garland", "x": -3, "y": 16},
    {"skill_id": "add_gold_ribbons", "x": -1, "y": 16},
    {"skill_id": "weave_garland", "x": 1, "y": 16},
    {"skill_id": "spiral_garland", "x": 0, "y": 18},
    {"skill_id": "craft_star_base", "x": -2, "y": 20},
    {"skill_id": "first_star_point", "x": -1, "y": 22},
    {"skill_id": "complete_star_shape", "x": 0, "y": 24},
    {"skill_id": "install_star_holder", "x": 1, "y": 22},
    {"skill_id": "place_star", "x": 0, "y": 26},
    {"skill_id": "activate_star", "x": -1, "y": 28},
    {"skill_id": "glowing_star", "x": 0, "y": 30},
    {"skill_id": "pulsating_star", "x": 1, "y": 28},
    {"skill_id": "animated_star", "x": 0, "y": 32},
    {"skill_id": "tree_perfection", "x": 0, "y": 34},
    {"skill_id": "advanced_light_prog", "x": -2, "y": 30},
    {"skill_id": "ornament_mastery", "x": -2, "y": 24},
    {"skill_id": "garland_harmony", "x": -3, "y": 20},
    {"skill_id": "cascading_ornaments", "x": 2, "y": 24},
    {"skill_id": "automated_decoration", "x": 2, "y": 28},
    {"skill_id": "synchronized_decor", "x": 1, "y": 30},
    {"skill_id": "ultimate_light_show", "x": -1, "y": 34},
    {"skill_id": "power_light_network", "x": 1, "y": 34},
    {"skill_id": "perfect_star_alignment", "x": 0, "y": 36}
  ]
}
